setup.cfg
setup.py
lmi/__init__.py
lmi/scripts/__init__.py
lmi/scripts/storage/__init__.py
lmi/scripts/storage/common.py
lmi/scripts/storage/fs.py
lmi/scripts/storage/luks.py
lmi/scripts/storage/lvm.py
lmi/scripts/storage/mount.py
lmi/scripts/storage/partition.py
lmi/scripts/storage/raid.py
lmi/scripts/storage/show.py
lmi/scripts/storage/storage_cmd.py
lmi/scripts/storage/cmd/__init__.py
lmi/scripts/storage/cmd/fs.py
lmi/scripts/storage/cmd/luks.py
lmi/scripts/storage/cmd/lv.py
lmi/scripts/storage/cmd/mount.py
lmi/scripts/storage/cmd/partition.py
lmi/scripts/storage/cmd/partition_table.py
lmi/scripts/storage/cmd/raid.py
lmi/scripts/storage/cmd/thinlv.py
lmi/scripts/storage/cmd/thinpool.py
lmi/scripts/storage/cmd/vg.py
openlmi_scripts_storage.egg-info/PKG-INFO
openlmi_scripts_storage.egg-info/SOURCES.txt
openlmi_scripts_storage.egg-info/dependency_links.txt
openlmi_scripts_storage.egg-info/entry_points.txt
openlmi_scripts_storage.egg-info/namespace_packages.txt
openlmi_scripts_storage.egg-info/requires.txt
openlmi_scripts_storage.egg-info/top_level.txt