Metadata-Version: 1.1
Name: openlmi-scripts-storage
Version: 0.0.4
Summary: LMI command for system storage administration.
Home-page: https://github.com/openlmi/openlmi-scripts
Author: Jan Safranek
Author-email: jsafrane@redhat.com
License: BSD
Download-URL: https://github.com/openlmi/openlmi-scripts/tarball/master
Platform: Any
Classifier: License :: OSI Approved :: BSD License
Classifier: Operating System :: POSIX :: Linux
Classifier: Topic :: System :: Systems Administration
Classifier: Programming Language :: Python
Classifier: Programming Language :: Python :: 2
Classifier: Programming Language :: Python :: 2.7
Classifier: Intended Audience :: Developers
Classifier: Environment :: Console
